pysti/__init__.py
pysti/pysti.py
pysti-0.0.2.dist-info/LICENSE
pysti-0.0.2.dist-info/METADATA
pysti-0.0.2.dist-info/WHEEL
pysti-0.0.2.dist-info/top_level.txt
pysti-0.0.2.dist-info/RECORD
